ogg4osu/__init__.py
ogg4osu/__main__.py
ogg4osu/audio.py
ogg4osu/cli.py
ogg4osu/ogg4osu.py
ogg4osu/audio/__init__.py
ogg4osu/audio/audio.py
ogg4osu/audio/audio_info.py
ogg4osu-0.2.0.dist-info/LICENSE
ogg4osu-0.2.0.dist-info/METADATA
ogg4osu-0.2.0.dist-info/WHEEL
ogg4osu-0.2.0.dist-info/top_level.txt
ogg4osu-0.2.0.dist-info/RECORD
