Metadata-Version: 2.1
Name: ogg4osu
Version: 0.2.0
Summary: Converts audio to OGG Vorbis for the purposes of osu!
Home-page: https://github.com/lewskii/ogg4osu
Author: lewski
Keywords: osu! mapping convert music audio ogg
Classifier: Development Status :: 3 - Alpha
Classifier: Environment :: Console
Classifier: Intended Audience :: End Users/Desktop
Classifier: License :: OSI Approved :: GNU General Public License v3 or later (GPLv3+)
Classifier: Natural Language :: English
Classifier: Programming Language :: Python :: 3
Classifier: Programming Language :: Python :: 3.11
Classifier: Topic :: Utilities
License-File: LICENSE
Requires-Dist: ffmpeg-python
